psychicdev/__init__.py
psychicdev/psychic.py
psychicdev-0.1.dist-info/METADATA
psychicdev-0.1.dist-info/WHEEL
psychicdev-0.1.dist-info/top_level.txt
psychicdev-0.1.dist-info/RECORD
