Metadata-Version: 2.1
Name: psychicdev
Version: 0.1
Summary: Psychic.dev is an open-source universal data connector for knowledgebases.
Home-page: UNKNOWN
Author: Ayan Bandyopadhyay
Author-email: ayan@getsidekick.ai
License: UNKNOWN
Platform: UNKNOWN
Requires-Dist: requests
